{
  "plugin": "NYSTHI",
  "model": "TZMX",
  "version": "2.4.23",
  "params": [
    {
      "id": 0,
      "name": "Input Level",
      "default": 1.41421,
      "min": 0,
      "max": 2
    },
    {
      "id": 1,
      "name": "Input Level",
      "default": 1.41421,
      "min": 0,
      "max": 2
    },
    {
      "id": 2,
      "name": "Input Level",
      "default": 1.41421,
      "min": 0,
      "max": 2
    },
    {
      "id": 3,
      "name": "Input Level",
      "default": 1.41421,
      "min": 0,
      "max": 2
    },
    {
      "id": 4,
      "name": "Input Level",
      "default": 1.41421,
      "min": 0,
      "max": 2
    },
    {
      "id": 5,
      "name": "Input Level",
      "default": 1.41421,
      "min": 0,
      "max": 2
    },
    {
      "id": 6,
      "name": "Ouput Level",
      "default": 1.41421,
      "min": 0,
      "max": 2
    }
  ]
}