{
  "plugin": "VultModulesFree",
  "model": "Opulus",
  "version": "2.0.16",
  "params": [
    {
      "id": 0,
      "name": "Osc 1 Frequency Multiplier",
      "default": 1,
      "min": 0,
      "max": 15
    },
    {
      "id": 1,
      "name": "Osc 2 Frequency Multiplier",
      "default": 1,
      "min": 0,
      "max": 15
    },
    {
      "id": 2,
      "name": "Osc 1 Feedback",
      "default": 0,
      "min": 0,
      "max": 7
    },
    {
      "id": 3,
      "name": "Mode (FM, Additive)",
      "default": 0,
      "min": 0,
      "max": 1
    },
    {
      "id": 4,
      "name": "Osc 1 Level",
      "default": 0,
      "min": 0,
      "max": 63
    },
    {
      "id": 5,
      "name": "Osc 1 Attack",
      "default": 0,
      "min": 0,
      "max": 15
    },
    {
      "id": 6,
      "name": "Osc 1 Decay",
      "default": 0,
      "min": 0,
      "max": 15
    },
    {
      "id": 7,
      "name": "Osc 1 Sustain",
      "default": 15,
      "min": 0,
      "max": 15
    },
    {
      "id": 8,
      "name": "Osc 1 Release",
      "default": 0,
      "min": 0,
      "max": 15
    },
    {
      "id": 9,
      "name": "Osc 2 Level",
      "default": 63,
      "min": 0,
      "max": 63
    },
    {
      "id": 10,
      "name": "Osc 2 Attack",
      "default": 0,
      "min": 0,
      "max": 15
    },
    {
      "id": 11,
      "name": "Osc 2 Decay",
      "default": 0,
      "min": 0,
      "max": 15
    },
    {
      "id": 12,
      "name": "Osc 2 Sustain",
      "default": 15,
      "min": 0,
      "max": 15
    },
    {
      "id": 13,
      "name": "Osc 2 Release",
      "default": 0,
      "min": 0,
      "max": 15
    },
    {
      "id": 14,
      "name": "Osc 1 Waveshape",
      "default": 0,
      "min": 0,
      "max": 1
    },
    {
      "id": 15,
      "name": "Osc 1 Envelope Mode",
      "default": 0,
      "min": 0,
      "max": 1
    },
    {
      "id": 16,
      "name": "Osc 2 Waveshape",
      "default": 0,
      "min": 0,
      "max": 1
    },
    {
      "id": 17,
      "name": "Osc 2 Envelope Mode",
      "default": 0,
      "min": 0,
      "max": 1
    },
    {
      "id": 18,
      "name": "Space Effect",
      "default": 0,
      "min": 0,
      "max": 1
    },
    {
      "id": 19,
      "name": "Osc 1 Velocity Effect",
      "default": 0,
      "min": 0,
      "max": 1
    },
    {
      "id": 20,
      "name": "Osc 2 Velocity Effect",
      "default": 0,
      "min": 0,
      "max": 1
    },
    {
      "id": 21,
      "name": "Modulation 1 Level",
      "default": 0,
      "min": -1,
      "max": 1
    },
    {
      "id": 22,
      "name": "Modulation 1 Selector",
      "default": 0,
      "min": 0,
      "max": 1
    },
    {
      "id": 23,
      "name": "Modulation 2 Level",
      "default": 0,
      "min": -1,
      "max": 1
    },
    {
      "id": 24,
      "name": "Modulation 2 Selector",
      "default": 0,
      "min": 0,
      "max": 1
    },
    {
      "id": 25,
      "name": "Back Menu",
      "default": 0,
      "min": 0,
      "max": 1
    },
    {
      "id": 26,
      "name": "Move Down",
      "default": 0,
      "min": 0,
      "max": 1
    },
    {
      "id": 27,
      "name": "Ok",
      "default": 0,
      "min": 0,
      "max": 1
    },
    {
      "id": 28,
      "name": "Move Up",
      "default": 0,
      "min": 0,
      "max": 1
    },
    {
      "id": 29,
      "name": "Slot Morph",
      "default": 0,
      "min": 0,
      "max": 1
    },
    {
      "id": 30,
      "name": "Slot 1 (long press to save)",
      "default": 0,
      "min": 0,
      "max": 1
    },
    {
      "id": 31,
      "name": "Slot 2 (long press to save)",
      "default": 0,
      "min": 0,
      "max": 1
    },
    {
      "id": 32,
      "name": "Slot 3 (long press to save)",
      "default": 0,
      "min": 0,
      "max": 1
    },
    {
      "id": 33,
      "name": "Slot 4 (long press to save)",
      "default": 0,
      "min": 0,
      "max": 1
    }
  ]
}