{
  "plugin": "dBiz",
  "model": "Contorno",
  "version": "2.1",
  "params": [
    {
      "id": 0,
      "name": "Ch range",
      "default": 0,
      "min": 0,
      "max": 2
    },
    {
      "id": 1,
      "name": "Ch range",
      "default": 0,
      "min": 0,
      "max": 2
    },
    {
      "id": 2,
      "name": "Ch range",
      "default": 0,
      "min": 0,
      "max": 2
    },
    {
      "id": 3,
      "name": "Ch range",
      "default": 0,
      "min": 0,
      "max": 2
    },
    {
      "id": 4,
      "name": "trig",
      "default": 0,
      "min": 0,
      "max": 1
    },
    {
      "id": 5,
      "name": "trig",
      "default": 0,
      "min": 0,
      "max": 1
    },
    {
      "id": 6,
      "name": "trig",
      "default": 0,
      "min": 0,
      "max": 1
    },
    {
      "id": 7,
      "name": "trig",
      "default": 0,
      "min": 0,
      "max": 1
    },
    {
      "id": 8,
      "name": "Ch cycle",
      "default": 0,
      "min": 0,
      "max": 1
    },
    {
      "id": 9,
      "name": "Ch cycle",
      "default": 0,
      "min": 0,
      "max": 1
    },
    {
      "id": 10,
      "name": "Ch cycle",
      "default": 0,
      "min": 0,
      "max": 1
    },
    {
      "id": 11,
      "name": "Ch cycle",
      "default": 0,
      "min": 0,
      "max": 1
    },
    {
      "id": 12,
      "name": "Shape",
      "default": 0,
      "min": -1,
      "max": 1
    },
    {
      "id": 13,
      "name": "Shape",
      "default": 0,
      "min": -1,
      "max": 1
    },
    {
      "id": 14,
      "name": "Shape",
      "default": 0,
      "min": -1,
      "max": 1
    },
    {
      "id": 15,
      "name": "Shape",
      "default": 0,
      "min": -1,
      "max": 1
    },
    {
      "id": 16,
      "name": "Raise",
      "default": 0,
      "min": 0,
      "max": 1
    },
    {
      "id": 17,
      "name": "Raise",
      "default": 0,
      "min": 0,
      "max": 1
    },
    {
      "id": 18,
      "name": "Raise",
      "default": 0,
      "min": 0,
      "max": 1
    },
    {
      "id": 19,
      "name": "Raise",
      "default": 0,
      "min": 0,
      "max": 1
    },
    {
      "id": 20,
      "name": "Fall",
      "default": 0,
      "min": 0,
      "max": 1
    },
    {
      "id": 21,
      "name": "Fall",
      "default": 0,
      "min": 0,
      "max": 1
    },
    {
      "id": 22,
      "name": "Fall",
      "default": 0,
      "min": 0,
      "max": 1
    },
    {
      "id": 23,
      "name": "Fall",
      "default": 0,
      "min": 0,
      "max": 1
    }
  ]
}