{
  "plugin": "ImpromptuModular",
  "model": "Chord-Key-Expander",
  "version": "2.5.0",
  "params": [
    {
      "id": 0,
      "name": "Oct channel 1",
      "default": 0,
      "min": -4,
      "max": 4
    },
    {
      "id": 1,
      "name": "Oct channel 2",
      "default": 0,
      "min": -4,
      "max": 4
    },
    {
      "id": 2,
      "name": "Oct channel 3",
      "default": 0,
      "min": -4,
      "max": 4
    },
    {
      "id": 3,
      "name": "Oct channel 4",
      "default": 0,
      "min": -4,
      "max": 4
    }
  ]
}